{"pi_id": "RPiID-00000000a1007a15", "date": "2024-07-11", "species": [{"12-20-52_dur=600secs_5": {"Class": "Eudynamys-scolopaceus", "Score": 0.2066071331501007}, "12-20-52_dur=600secs_10": {"Class": "Phyllergates-cucullatus", "Score": 0.33830031752586365}, "12-20-52_dur=600secs_15": {"Class": "Phyllergates-cucullatus", "Score": 0.5118876099586487}, "12-20-52_dur=600secs_20": {"Class": "Phyllergates-cucullatus", "Score": 0.6580435633659363}, "12-20-52_dur=600secs_25": {"Class": "Phyllergates-cucullatus", "Score": 0.3215999901294708}, "12-20-52_dur=600secs_30": {"Class": "Alcedo-atthis", "Score": 0.26509878039360046}, "12-20-52_dur=600secs_35": {"Class": "Phyllergates-cucullatus", "Score": 0.4442973732948303}, "12-20-52_dur=600secs_40": {"Class": "Alcedo-atthis", "Score": 0.31812992691993713}, "12-20-52_dur=600secs_45": {"Class": "Alcedo-atthis", "Score": 0.2647046148777008}, "12-20-52_dur=600secs_50": {"Class": "Alcedo-atthis", "Score": 0.2302423119544983}, "12-20-52_dur=600secs_55": {"Class": "Phyllergates-cucullatus", "Score": 0.7972316145896912}, "12-20-52_dur=600secs_60": {"Class": "Phyllergates-cucullatus", "Score": 0.6138095855712891}, "12-20-52_dur=600secs_65": {"Class": "Alcedo-atthis", "Score": 0.27574023604393005}, "12-20-52_dur=600secs_70": {"Class": "Alcedo-atthis", "Score": 0.256098210811615}, "12-20-52_dur=600secs_75": {"Class": "Alcedo-atthis", "Score": 0.3150824010372162}, "12-20-52_dur=600secs_80": {"Class": "Phyllergates-cucullatus", "Score": 0.23846708238124847}, "12-20-52_dur=600secs_85": {"Class": "Phyllergates-cucullatus", "Score": 0.3385290205478668}, "12-20-52_dur=600secs_90": {"Class": "Eudynamys-scolopaceus", "Score": 0.25829562544822693}, "12-20-52_dur=600secs_95": {"Class": "Eudynamys-scolopaceus", "Score": 0.258197158575058}, "12-20-52_dur=600secs_100": {"Class": "Gallus-gallus", "Score": 0.13574427366256714}, "12-20-52_dur=600secs_105": {"Class": "Eudynamys-scolopaceus", "Score": 0.267441064119339}, "12-20-52_dur=600secs_110": {"Class": "Eudynamys-scolopaceus", "Score": 0.2562605142593384}, "12-20-52_dur=600secs_115": {"Class": "Eudynamys-scolopaceus", "Score": 0.32538485527038574}, "12-20-52_dur=600secs_120": {"Class": "Parus-minor", "Score": 0.36503395438194275}, "12-20-52_dur=600secs_125": {"Class": "Eudynamys-scolopaceus", "Score": 0.23163221776485443}, "12-20-52_dur=600secs_130": {"Class": "Eudynamys-scolopaceus", "Score": 0.16443105041980743}, "12-20-52_dur=600secs_135": {"Class": "Eudynamys-scolopaceus", "Score": 0.20415957272052765}, "12-20-52_dur=600secs_140": {"Class": "Alcedo-atthis", "Score": 0.26875633001327515}, "12-20-52_dur=600secs_145": {"Class": "Alcedo-atthis", "Score": 0.25808775424957275}, "12-20-52_dur=600secs_150": {"Class": "Alcedo-atthis", "Score": 0.27763620018959045}, "12-20-52_dur=600secs_155": {"Class": "Alcedo-atthis", "Score": 0.2315303087234497}, "12-20-52_dur=600secs_160": {"Class": "Cacomantis-merulinus", "Score": 0.2885206937789917}, "12-20-52_dur=600secs_165": {"Class": "Phyllergates-cucullatus", "Score": 0.33931201696395874}, "12-20-52_dur=600secs_170": {"Class": "Eudynamys-scolopaceus", "Score": 0.27496421337127686}, "12-20-52_dur=600secs_175": {"Class": "Alcedo-atthis", "Score": 0.3519766628742218}, "12-20-52_dur=600secs_180": {"Class": "Phyllergates-cucullatus", "Score": 0.21833789348602295}, "12-20-52_dur=600secs_185": {"Class": "Alcedo-atthis", "Score": 0.29590660333633423}, "12-20-52_dur=600secs_190": {"Class": "Phyllergates-cucullatus", "Score": 0.21740855276584625}, "12-20-52_dur=600secs_195": {"Class": "Centropus-sinensis", "Score": 0.30947571992874146}, "12-20-52_dur=600secs_200": {"Class": "Alcedo-atthis", "Score": 0.2531462013721466}, "12-20-52_dur=600secs_205": {"Class": "Alcedo-atthis", "Score": 0.2995755672454834}, "12-20-52_dur=600secs_210": {"Class": "Alcedo-atthis", "Score": 0.33109304308891296}, "12-20-52_dur=600secs_215": {"Class": "Phyllergates-cucullatus", "Score": 0.5257149934768677}, "12-20-52_dur=600secs_220": {"Class": "Alcedo-atthis", "Score": 0.28889140486717224}, "12-20-52_dur=600secs_225": {"Class": "Phyllergates-cucullatus", "Score": 0.5923318266868591}, "12-20-52_dur=600secs_230": {"Class": "Phyllergates-cucullatus", "Score": 0.5037345886230469}, "12-20-52_dur=600secs_235": {"Class": "Alcedo-atthis", "Score": 0.35457319021224976}, "12-20-52_dur=600secs_240": {"Class": "Alcedo-atthis", "Score": 0.3418489992618561}, "12-20-52_dur=600secs_245": {"Class": "Alcedo-atthis", "Score": 0.29854610562324524}, "12-20-52_dur=600secs_250": {"Class": "Phyllergates-cucullatus", "Score": 0.5145590901374817}, "12-20-52_dur=600secs_255": {"Class": "Alcedo-atthis", "Score": 0.3247329592704773}, "12-20-52_dur=600secs_260": {"Class": "Alcedo-atthis", "Score": 0.21986913681030273}, "12-20-52_dur=600secs_265": {"Class": "Alcedo-atthis", "Score": 0.307785302400589}, "12-20-52_dur=600secs_270": {"Class": "Parus-minor", "Score": 0.2897469997406006}, "12-20-52_dur=600secs_275": {"Class": "Alcedo-atthis", "Score": 0.15367457270622253}, "12-20-52_dur=600secs_280": {"Class": "Eudynamys-scolopaceus", "Score": 0.1775636374950409}, "12-20-52_dur=600secs_285": {"Class": "Alcedo-atthis", "Score": 0.33772367238998413}, "12-20-52_dur=600secs_290": {"Class": "Alcedo-atthis", "Score": 0.21805356442928314}, "12-20-52_dur=600secs_295": {"Class": "Alcedo-atthis", "Score": 0.2395225316286087}, "12-20-52_dur=600secs_300": {"Class": "Hirundo-rustica", "Score": 0.16955743730068207}, "12-20-52_dur=600secs_305": {"Class": "Hirundo-rustica", "Score": 0.13141879439353943}}]}